hiutils/__init__.py
hiutils/core.py
hiutils_aymen-0.1.9.dist-info/METADATA
hiutils_aymen-0.1.9.dist-info/WHEEL
hiutils_aymen-0.1.9.dist-info/top_level.txt
hiutils_aymen-0.1.9.dist-info/RECORD
