Metadata-Version: 2.4
Name: hiutils-aymen
Version: 0.1.9
Summary: Shared utilities for hierarchical interaction regression (UniLasso, Lasso, OLS, CV utilities).
Author: Aymen Echarghaoui
License: MIT
Keywords: lasso,statistics,interactions,machine-learning,scikit-learn
Classifier: Programming Language :: Python :: 3
Classifier: License :: OSI Approved :: MIT License
Classifier: Intended Audience :: Science/Research
Classifier: Topic :: Scientific/Engineering
Requires-Python: >=3.9
Requires-Dist: numpy>=1.22
Requires-Dist: scipy>=1.9
Requires-Dist: scikit-learn>=1.1
Requires-Dist: matplotlib>=3.5
Requires-Dist: seaborn>=0.11
Requires-Dist: adelie>=0.2
